{
  "variants": {
    "larvae=true": [
      {
        "model": "virtual_additions:block/lumwasp_nest_larvae_1a"
      },
      {
        "model": "virtual_additions:block/lumwasp_nest_larvae_1b"
      },
      {
        "model": "virtual_additions:block/lumwasp_nest_larvae_1c"
      },
      {
        "model": "virtual_additions:block/lumwasp_nest_larvae_1d"
      },
      {
        "model": "virtual_additions:block/lumwasp_nest_larvae_2a"
      },
      {
        "model": "virtual_additions:block/lumwasp_nest_larvae_2b"
      },
      {
        "model": "virtual_additions:block/lumwasp_nest_larvae_2c"
      },
      {
        "model": "virtual_additions:block/lumwasp_nest_larvae_2d"
      },
      {
        "model": "virtual_additions:block/lumwasp_nest_larvae_2e"
      },
      {
        "model": "virtual_additions:block/lumwasp_nest_larvae_2f"
      },
      {
        "model": "virtual_additions:block/lumwasp_nest_larvae_3a"
      },
      {
        "model": "virtual_additions:block/lumwasp_nest_larvae_3b"
      },
      {
        "model": "virtual_additions:block/lumwasp_nest_larvae_3c"
      },
      {
        "model": "virtual_additions:block/lumwasp_nest_larvae_3d"
      },
      {
        "model": "virtual_additions:block/lumwasp_nest_larvae"
      }
    ],
    "larvae=false": {
      "model": "virtual_additions:block/lumwasp_nest"
    }
  }
}
